README.md
setup.py
RealmKeeper.egg-info/PKG-INFO
RealmKeeper.egg-info/SOURCES.txt
RealmKeeper.egg-info/dependency_links.txt
RealmKeeper.egg-info/entry_points.txt
RealmKeeper.egg-info/requires.txt
RealmKeeper.egg-info/top_level.txt
realmkeeper/__init__.py
realmkeeper/__main__.py
realmkeeper/app.py
realmkeeper/aws.py
realmkeeper/config.py
realmkeeper/ipa.py
realmkeeper/realmkeeper.py