Metadata-Version: 2.1
Name: RealmKeeper
Version: 0.1.3
Summary: Python Utility to manage hosts with FreeIPA
Home-page: UNKNOWN
Author: Jake Neyer
Author-email: jaken551@gmail.com
License: UNKNOWN
Platform: UNKNOWN
